GEOS5FP/GEOS5FP.py
GEOS5FP/GEOS5FP_connection.py
GEOS5FP/GEOS5FP_granule.py
GEOS5FP/GEOS5FP_point.py
GEOS5FP/HTTP_listing.py
GEOS5FP/VARIABLES_README.md
GEOS5FP/__init__.py
GEOS5FP/calculate_RH.py
GEOS5FP/cluster_times.py
GEOS5FP/constants.py
GEOS5FP/create_legacy_ssl_context.py
GEOS5FP/create_robust_session.py
GEOS5FP/download_file.py
GEOS5FP/exceptions.py
GEOS5FP/geometry_utils.py
GEOS5FP/get_variable_info.py
GEOS5FP/make_head_request_with_ssl_fallback.py
GEOS5FP/query.py
GEOS5FP/validate_GEOS5FP_NetCDF_file.py
GEOS5FP/variables.csv
GEOS5FP/version.py
GEOS5FP/downscaling/__init__.py
GEOS5FP/downscaling/downscaling.py
GEOS5FP/timer/__init__.py
GEOS5FP/timer/timer.py
geos5fp-2.19.0.dist-info/licenses/LICENSE
geos5fp-2.19.0.dist-info/METADATA
geos5fp-2.19.0.dist-info/WHEEL
geos5fp-2.19.0.dist-info/top_level.txt
geos5fp-2.19.0.dist-info/RECORD
