Metadata-Version: 2.4
Name: GEOS5FP
Version: 2.19.0
Summary: generates rasters of near-real-time GEOS-5 FP near-surface meteorology
Author-email: "Gregory H. Halverson" <gregory.h.halverson@jpl.nasa.gov>
Project-URL: Homepage, https://github.com/JPL-Evapotranspiration-Algorithms/GEOS5FP
Classifier: Programming Language :: Python :: 3
Classifier: Operating System :: OS Independent
Requires-Python: >=3.10
License-File: LICENSE
Requires-Dist: affine
Requires-Dist: beautifulsoup4
Requires-Dist: colored-logging
Requires-Dist: dask
Requires-Dist: ECOv002-calval-tables>=1.11.0
Requires-Dist: geopandas>=1.1.1
Requires-Dist: matplotlib
Requires-Dist: netcdf4
Requires-Dist: numpy
Requires-Dist: pandas
Requires-Dist: pyproj
Requires-Dist: python-dateutil
Requires-Dist: pytictoc
Requires-Dist: rasterio
Requires-Dist: rasters>=1.13.2
Requires-Dist: requests
Requires-Dist: scipy
Requires-Dist: sentinel-tiles
Requires-Dist: shapely
Requires-Dist: urllib3
Requires-Dist: xarray
Provides-Extra: dev
Requires-Dist: build; extra == "dev"
Requires-Dist: pytest>=6.0; extra == "dev"
Requires-Dist: pytest-cov; extra == "dev"
Requires-Dist: jupyter; extra == "dev"
Requires-Dist: pytest; extra == "dev"
Requires-Dist: twine; extra == "dev"
Dynamic: license-file
